README.rst
setup.py
setuptools_tasks/__init__.py
setuptools_tasks/sdist.py
setuptools_tasks/statics_building.py
setuptools_tasks/utils.py
setuptools_tasks.egg-info/PKG-INFO
setuptools_tasks.egg-info/SOURCES.txt
setuptools_tasks.egg-info/dependency_links.txt
setuptools_tasks.egg-info/entry_points.txt
setuptools_tasks.egg-info/pbr.json
setuptools_tasks.egg-info/requires.txt
setuptools_tasks.egg-info/top_level.txt
setuptools_tasks/tests/__init__.py
setuptools_tasks/tests/test_sdist.py
setuptools_tasks/tests/test_static_building.py
setuptools_tasks/tests/utils.py