Metadata-Version: 1.1
Name: setuptools-tasks
Version: 0.1.0
Summary: Augments setuptools lifecycle.
Home-page: https://github.com/pbs/setuptools-tasks
Author: PBS Bento Web Services Team
Author-email: TPG-PBS-Bento@3pillarglobal.com
License: UNKNOWN
Keywords: setuptools sass
Platform: any
Classifier: Programming Language :: Python :: 2.6
Classifier: Programming Language :: Python :: 2.7
Classifier: Programming Language :: Python :: 3
Classifier: Programming Language :: Python :: 3.3
Classifier: Programming Language :: Python :: 3.4
Classifier: Programming Language :: Python :: 3.5
Classifier: Operating System :: MacOS :: MacOS X
Classifier: Operating System :: POSIX :: Linux
Classifier: Topic :: Software Development :: Build Tools
